legacycrypt.py
legacycrypt-0.3.dist-info/LICENSE
legacycrypt-0.3.dist-info/WHEEL
legacycrypt-0.3.dist-info/METADATA
legacycrypt-0.3.dist-info/RECORD
