Metadata-Version: 2.1
Name: legacycrypt
Version: 0.3
Summary: Wrapper to the POSIX crypt library call and associated functionality.
Home-page: https://github.com/tiran/legacycrypt
License: UNKNOWN
Author: Christian Heimes
Author-email: christian@python.org
Maintainer: Christian Heimes
Maintainer-email: christian@python.org
Requires-Python: >=3.5
Classifier: Development Status :: 5 - Production/Stable
Classifier: Programming Language :: Python :: 3.6
Classifier: Programming Language :: Python :: 3.7
Classifier: Programming Language :: Python :: 3.8
Classifier: Programming Language :: Python :: 3 :: Only
Classifier: Programming Language :: Python :: Implementation :: CPython
Classifier: Programming Language :: Python :: Implementation :: PyPy
Classifier: Intended Audience :: Developers
Classifier: License :: OSI Approved :: Python Software Foundation License
Classifier: Operating System :: POSIX
Classifier: Topic :: Security :: Cryptography
